tensoract/__init__.py
tensoract/client.py
tensoract-1.0.3.dist-info/LICENSE
tensoract-1.0.3.dist-info/METADATA
tensoract-1.0.3.dist-info/WHEEL
tensoract-1.0.3.dist-info/top_level.txt
tensoract-1.0.3.dist-info/RECORD
