Metadata-Version: 2.1
Name: tensoract
Version: 1.0.3
Summary: Python api client - https://api.tensoract.com/docs
Home-page: https://github.com/deepalirajale/newton-api
Author: Tensoract Inc.
Author-email: support@tensoract.com
Project-URL: Bug Tracker, https://github.com/deepalirajale/newton-api/issues
Classifier: Programming Language :: Python :: 3
Classifier: License :: OSI Approved :: MIT License
Classifier: Operating System :: OS Independent
Requires-Python: >=3.6
License-File: LICENSE
